settingsfile/__init__.py
settingsfile/main.py
settingsfile-1.0.2.dist-info/LICENSE
settingsfile-1.0.2.dist-info/METADATA
settingsfile-1.0.2.dist-info/WHEEL
settingsfile-1.0.2.dist-info/top_level.txt
settingsfile-1.0.2.dist-info/RECORD
