Metadata-Version: 2.1
Name: settingsfile
Version: 1.0.2
Summary: Memorize settings in Python easily. Autoload and autosave settings to a file.
Home-page: https://github.com/divisia/settingsfile
Author: Ömer Selçuk
Author-email: omrfyyz@gmail.com
License: UNKNOWN
Platform: UNKNOWN
Classifier: Programming Language :: Python :: 3
Classifier: License :: OSI Approved :: MIT License
Classifier: Operating System :: OS Independent
Requires-Python: >=3.6
